literature_analysis/__init__.py
literature_analysis/analyze.py
literature_analysis/analyze_final.py
literature_analysis/main.py
literature_analysis/process.py
literature_analysis/search.py
literature_analysis/visualize.py
literature_analysis-1.0.1.dist-info/METADATA
literature_analysis-1.0.1.dist-info/WHEEL
literature_analysis-1.0.1.dist-info/entry_points.txt
literature_analysis-1.0.1.dist-info/top_level.txt
literature_analysis-1.0.1.dist-info/RECORD
