Metadata-Version: 2.4
Name: literature-analysis
Version: 1.0.1
Summary: A tool for literature analysis
Author-email: Tswi <1321333@zju.edu.cn>
Requires-Python: >=3.6
Requires-Dist: requests>=2.31.0
Requires-Dist: aiohttp>=3.9.1
Requires-Dist: openai>=1.3.7
Requires-Dist: pandas>=2.1.4
Requires-Dist: openpyxl>=3.1.2
Requires-Dist: reportlab>=4.0.8
Requires-Dist: python-dotenv>=1.0.0
Requires-Dist: tqdm>=4.66.1
